{"nm":"battery_icon_vector","v":"5.9.6","fr":60,"ip":0,"op":479,"w":478,"h":271,"ddd":0,"markers":[],"assets":[{"nm":"battery_icon_vector","fr":60,"id":"lwg7cea241s47sef","layers":[{"ty":3,"ddd":0,"ind":5,"hd":false,"nm":"battery_icon_vector - Null","ks":{"a":{"a":0,"k":[0,0]},"o":{"a":0,"k":100},"p":{"a":0,"k":[0,0]},"r":{"a":0,"k":0},"s":{"a":0,"k":[100,100]},"sk":{"a":0,"k":0},"sa":{"a":0,"k":0}},"st":0,"ip":0,"op":480,"bm":0,"sr":1},{"ty":3,"ddd":0,"ind":6,"hd":false,"nm":"Ellipse 1 - Null","parent":5,"ks":{"a":{"a":0,"k":[90.5,90.5]},"o":{"a":0,"k":100},"p":{"a":0,"k":[248.5,131.5]},"r":{"a":0,"k":0},"s":{"a":1,"k":[{"t":145.3445378151247,"s":[0.1,0.1],"o":{"x":[0.5],"y":[0.35]},"i":{"x":[0.15],"y":[1]}},{"t":193.34453781512474,"s":[100,100]}]},"sk":{"a":0,"k":0},"sa":{"a":0,"k":0}},"st":0,"ip":0,"op":480,"bm":0,"sr":1},{"ty":4,"ddd":0,"ind":7,"hd":false,"nm":"Ellipse 1","parent":6,"ks":{"a":{"a":0,"k":[0,0]},"p":{"a":0,"k":[0,0]},"s":{"a":0,"k":[100,100]},"sk":{"a":0,"k":0},"sa":{"a":0,"k":0},"r":{"a":0,"k":0},"o":{"a":0,"k":100}},"st":0,"ip":0,"op":480,"bm":0,"sr":1,"shapes":[{"ty":"gr","nm":"Group","hd":false,"np":3,"it":[{"ty":"sh","nm":"Path","hd":false,"ks":{"a":0,"k":{"c":true,"v":[[181,90.5],[90.5,181],[0,90.5],[90.5,0],[181,90.5],[181,90.5]],"i":[[0,-49.98320000000001],[49.9832,0],[0,49.9832],[-49.9831,0],[0,-49.9831],[0,0]],"o":[[0,49.98320000000001],[-49.9831,0],[0,-49.9831],[49.98320000000001,0],[0,0],[0,0]]}}},{"ty":"fl","o":{"a":1,"k":[{"t":149.24369747899158,"s":[38],"o":{"x":[0.5],"y":[0.35]},"i":{"x":[0.15],"y":[1]}},{"t":151.26050420168065,"s":[40],"o":{"x":[0.5],"y":[0.35]},"i":{"x":[0.15],"y":[1]}},{"t":156.63865546218486,"s":[45],"o":{"x":[0.5],"y":[0.35]},"i":{"x":[0.15],"y":[1]}},{"t":168.06722689075633,"s":[50],"o":{"x":[0.5],"y":[0.35]},"i":{"x":[0.15],"y":[1]}},{"t":176.1344537815126,"s":[55.00000000000001],"o":{"x":[0.5],"y":[0.35]},"i":{"x":[0.15],"y":[1]}},{"t":183.52941176470586,"s":[60],"o":{"x":[0.5],"y":[0.35]},"i":{"x":[0.15],"y":[1]}},{"t":189.57983193277306,"s":[51],"o":{"x":[0.5],"y":[0.35]},"i":{"x":[0.15],"y":[1]}},{"t":206.3865546218487,"s":[57.99999999999999],"o":{"x":[0.5],"y":[0.35]},"i":{"x":[0.15],"y":[1]}},{"t":215.126050420168,"s":[0]}]},"c":{"a":1,"k":[{"t":149.24369747899158,"s":[0.6784313725490196,1,0,1],"o":{"x":[0.5],"y":[0.35]},"i":{"x":[0.15],"y":[1]}},{"t":151.26050420168065,"s":[0.6784313725490196,1,0,1],"o":{"x":[0.5],"y":[0.35]},"i":{"x":[0.15],"y":[1]}},{"t":156.63865546218486,"s":[0.6784313725490196,1,0,1],"o":{"x":[0.5],"y":[0.35]},"i":{"x":[0.15],"y":[1]}},{"t":168.06722689075633,"s":[0.6784313725490196,1,0,1],"o":{"x":[0.5],"y":[0.35]},"i":{"x":[0.15],"y":[1]}},{"t":176.1344537815126,"s":[0.6784313725490196,1,0,1],"o":{"x":[0.5],"y":[0.35]},"i":{"x":[0.15],"y":[1]}},{"t":183.52941176470586,"s":[0.6784313725490196,1,0,1],"o":{"x":[0.5],"y":[0.35]},"i":{"x":[0.15],"y":[1]}},{"t":189.57983193277306,"s":[0.023529411764705882,1,0.09411764705882353,1],"o":{"x":[0.5],"y":[0.35]},"i":{"x":[0.15],"y":[1]}},{"t":206.3865546218487,"s":[0.023529411764705882,1,0.09411764705882353,1],"o":{"x":[0.5],"y":[0.35]},"i":{"x":[0.15],"y":[1]}},{"t":215.126050420168,"s":[0.023529411764705882,1,0.09411764705882353,1]}]},"nm":"Fill","hd":false,"r":1},{"ty":"tr","a":{"a":0,"k":[0,0]},"p":{"a":0,"k":[0,0]},"s":{"a":0,"k":[100,100]},"sk":{"a":0,"k":0},"sa":{"a":0,"k":0},"r":{"a":0,"k":0},"o":{"a":0,"k":100}}]}]},{"ty":3,"ddd":0,"ind":8,"hd":false,"nm":"Line 4 - Null","parent":5,"ks":{"a":{"a":0,"k":[0,0]},"o":{"a":1,"k":[{"t":48,"s":[0],"o":{"x":[0.5],"y":[0.35]},"i":{"x":[0.15],"y":[1]}},{"t":138,"s":[100]}]},"p":{"a":0,"k":[299,159]},"r":{"a":0,"k":38.3513},"s":{"a":0,"k":[100,100]},"sk":{"a":0,"k":0},"sa":{"a":0,"k":0}},"st":0,"ip":0,"op":480,"bm":0,"sr":1},{"ddd":0,"ind":9,"hd":false,"nm":"Line 4 - Stroke","parent":8,"ks":{"a":{"a":0,"k":[0,0]},"p":{"a":0,"k":[0,0]},"s":{"a":0,"k":[100,100]},"sk":{"a":0,"k":0},"sa":{"a":0,"k":0},"r":{"a":0,"k":0},"o":{"a":1,"k":[{"t":48,"s":[0],"o":{"x":[0.5],"y":[0.35]},"i":{"x":[0.15],"y":[1]}},{"t":138,"s":[100]}]}},"st":0,"ip":0,"op":480,"bm":0,"sr":1,"ty":4,"shapes":[{"ty":"gr","nm":"Group","hd":false,"np":3,"it":[{"ty":"sh","nm":"Path","hd":false,"ks":{"a":0,"k":{"c":false,"v":[[0.5,-0.5],[115.5388,-0.5]],"i":[[0,0],[0,0]],"o":[[0,0],[0,0]]}}},{"ty":"st","o":{"a":1,"k":[{"t":48,"s":[100],"o":{"x":[0.5],"y":[0.35]},"i":{"x":[0.15],"y":[1]}},{"t":232.52941176470492,"s":[0]}]},"c":{"a":1,"k":[{"t":48,"s":[1,0.9607843137254902,0,1],"o":{"x":[0.5],"y":[0.35]},"i":{"x":[0.15],"y":[1]}},{"t":232.52941176470492,"s":[1,0.9607843137254902,0,1]}]},"w":{"a":0,"k":1},"ml":4,"lc":1,"lj":1,"nm":"Stroke","hd":false,"d":[{"n":"o","nm":"Offset","v":{"a":0,"k":0}},{"n":"d","nm":"Dash","v":{"a":0,"k":0}},{"n":"g","nm":"Gap","v":{"a":0,"k":0}}]},{"ty":"tr","a":{"a":0,"k":[0,0]},"p":{"a":0,"k":[0,0]},"s":{"a":0,"k":[100,100]},"sk":{"a":0,"k":0},"sa":{"a":0,"k":0},"r":{"a":0,"k":0},"o":{"a":0,"k":100}}]},{"ty":"gr","nm":"Group","hd":false,"np":3,"it":[{"ty":"rc","nm":"Rectangle","hd":false,"p":{"a":0,"k":[58.5194,0.5]},"s":{"a":0,"k":[234.0776,2]},"r":{"a":0,"k":0}},{"ty":"fl","o":{"a":0,"k":0},"c":{"a":0,"k":[0,1,0,1]},"nm":"Fill","hd":false,"r":1},{"ty":"tr","a":{"a":0,"k":[0,0]},"p":{"a":0,"k":[0,0]},"s":{"a":0,"k":[100,100]},"sk":{"a":0,"k":0},"sa":{"a":0,"k":0},"r":{"a":0,"k":0},"o":{"a":0,"k":100}}]}]},{"ty":3,"ddd":0,"ind":10,"hd":false,"nm":"Line 3 - Null","parent":5,"ks":{"a":{"a":0,"k":[0,0]},"o":{"a":1,"k":[{"t":48,"s":[0],"o":{"x":[0.5],"y":[0.35]},"i":{"x":[0.15],"y":[1]}},{"t":138,"s":[100]}]},"p":{"a":0,"k":[300,106]},"r":{"a":0,"k":-33.8351},"s":{"a":0,"k":[100,100]},"sk":{"a":0,"k":0},"sa":{"a":0,"k":0}},"st":0,"ip":0,"op":480,"bm":0,"sr":1},{"ddd":0,"ind":11,"hd":false,"nm":"Line 3 - Stroke","parent":10,"ks":{"a":{"a":0,"k":[0,0]},"p":{"a":0,"k":[0,0]},"s":{"a":0,"k":[100,100]},"sk":{"a":0,"k":0},"sa":{"a":0,"k":0},"r":{"a":0,"k":0},"o":{"a":1,"k":[{"t":48,"s":[0],"o":{"x":[0.5],"y":[0.35]},"i":{"x":[0.15],"y":[1]}},{"t":138,"s":[100]}]}},"st":0,"ip":0,"op":480,"bm":0,"sr":1,"ty":4,"shapes":[{"ty":"gr","nm":"Group","hd":false,"np":3,"it":[{"ty":"sh","nm":"Path","hd":false,"ks":{"a":0,"k":{"c":false,"v":[[0.5,-0.5],[109.0536,-0.5]],"i":[[0,0],[0,0]],"o":[[0,0],[0,0]]}}},{"ty":"st","o":{"a":1,"k":[{"t":48,"s":[100],"o":{"x":[0.5],"y":[0.35]},"i":{"x":[0.15],"y":[1]}},{"t":232.52941176470492,"s":[0]}]},"c":{"a":1,"k":[{"t":48,"s":[1,0.9607843137254902,0,1],"o":{"x":[0.5],"y":[0.35]},"i":{"x":[0.15],"y":[1]}},{"t":232.52941176470492,"s":[1,0.9607843137254902,0,1]}]},"w":{"a":0,"k":1},"ml":4,"lc":1,"lj":1,"nm":"Stroke","hd":false,"d":[{"n":"o","nm":"Offset","v":{"a":0,"k":0}},{"n":"d","nm":"Dash","v":{"a":0,"k":0}},{"n":"g","nm":"Gap","v":{"a":0,"k":0}}]},{"ty":"tr","a":{"a":0,"k":[0,0]},"p":{"a":0,"k":[0,0]},"s":{"a":0,"k":[100,100]},"sk":{"a":0,"k":0},"sa":{"a":0,"k":0},"r":{"a":0,"k":0},"o":{"a":0,"k":100}}]},{"ty":"gr","nm":"Group","hd":false,"np":3,"it":[{"ty":"rc","nm":"Rectangle","hd":false,"p":{"a":0,"k":[55.2768,0.5]},"s":{"a":0,"k":[221.1072,2]},"r":{"a":0,"k":0}},{"ty":"fl","o":{"a":0,"k":0},"c":{"a":0,"k":[0,1,0,1]},"nm":"Fill","hd":false,"r":1},{"ty":"tr","a":{"a":0,"k":[0,0]},"p":{"a":0,"k":[0,0]},"s":{"a":0,"k":[100,100]},"sk":{"a":0,"k":0},"sa":{"a":0,"k":0},"r":{"a":0,"k":0},"o":{"a":0,"k":100}}]}]},{"ty":3,"ddd":0,"ind":12,"hd":false,"nm":"Line 2 - Null","parent":5,"ks":{"a":{"a":0,"k":[50.55935,0]},"o":{"a":1,"k":[{"t":48,"s":[0],"o":{"x":[0.5],"y":[0.35]},"i":{"x":[0.15],"y":[1]}},{"t":138,"s":[100]}]},"p":{"a":0,"k":[116.49999490038081,194.0000348690132]},"r":{"a":0,"k":-28.3391},"s":{"a":1,"k":[{"t":48,"s":[100,100],"o":{"x":[0.5],"y":[0]},"i":{"x":[0.4],"y":[1]}},{"t":93,"s":[140,140]}]},"sk":{"a":0,"k":0},"sa":{"a":0,"k":0}},"st":0,"ip":0,"op":480,"bm":0,"sr":1},{"ddd":0,"ind":13,"hd":false,"nm":"Line 2 - Stroke","parent":12,"ks":{"a":{"a":0,"k":[0,0]},"p":{"a":0,"k":[0,0]},"s":{"a":0,"k":[100,100]},"sk":{"a":0,"k":0},"sa":{"a":0,"k":0},"r":{"a":0,"k":0},"o":{"a":1,"k":[{"t":48,"s":[0],"o":{"x":[0.5],"y":[0.35]},"i":{"x":[0.15],"y":[1]}},{"t":138,"s":[100]}]}},"st":0,"ip":0,"op":480,"bm":0,"sr":1,"ty":4,"shapes":[{"ty":"gr","nm":"Group","hd":false,"np":3,"it":[{"ty":"sh","nm":"Path","hd":false,"ks":{"a":0,"k":{"c":false,"v":[[0.5,-0.5],[100.6187,-0.5]],"i":[[0,0],[0,0]],"o":[[0,0],[0,0]]}}},{"ty":"st","o":{"a":1,"k":[{"t":48.512605042016176,"s":[75],"o":{"x":[0.5],"y":[0.35]},"i":{"x":[0.15],"y":[1]}},{"t":240.67226890756302,"s":[0]}]},"c":{"a":1,"k":[{"t":48.512605042016176,"s":[1,0.9607843137254902,0,1],"o":{"x":[0.5],"y":[0.35]},"i":{"x":[0.15],"y":[1]}},{"t":240.67226890756302,"s":[1,0.9607843137254902,0,1]}]},"w":{"a":0,"k":1},"ml":4,"lc":1,"lj":1,"nm":"Stroke","hd":false,"d":[{"n":"o","nm":"Offset","v":{"a":0,"k":0}},{"n":"d","nm":"Dash","v":{"a":0,"k":0}},{"n":"g","nm":"Gap","v":{"a":0,"k":0}}]},{"ty":"tr","a":{"a":0,"k":[0,0]},"p":{"a":0,"k":[0,0]},"s":{"a":0,"k":[100,100]},"sk":{"a":0,"k":0},"sa":{"a":0,"k":0},"r":{"a":0,"k":0},"o":{"a":0,"k":100}}]},{"ty":"gr","nm":"Group","hd":false,"np":3,"it":[{"ty":"rc","nm":"Rectangle","hd":false,"p":{"a":0,"k":[51.05935,0.5]},"s":{"a":0,"k":[204.2374,2]},"r":{"a":0,"k":0}},{"ty":"fl","o":{"a":0,"k":0},"c":{"a":0,"k":[0,1,0,1]},"nm":"Fill","hd":false,"r":1},{"ty":"tr","a":{"a":0,"k":[0,0]},"p":{"a":0,"k":[0,0]},"s":{"a":0,"k":[100,100]},"sk":{"a":0,"k":0},"sa":{"a":0,"k":0},"r":{"a":0,"k":0},"o":{"a":0,"k":100}}]}]},{"ty":3,"ddd":0,"ind":14,"hd":false,"nm":"Line 1 - Null","parent":5,"ks":{"a":{"a":0,"k":[0,0]},"o":{"a":1,"k":[{"t":48,"s":[0],"o":{"x":[0.5],"y":[0.35]},"i":{"x":[0.15],"y":[1]}},{"t":138,"s":[100]}]},"p":{"a":0,"k":[95,36]},"r":{"a":0,"k":38.0996},"s":{"a":0,"k":[100,100]},"sk":{"a":0,"k":0},"sa":{"a":0,"k":0}},"st":0,"ip":0,"op":480,"bm":0,"sr":1},{"ddd":0,"ind":15,"hd":false,"nm":"Line 1 - Stroke","parent":14,"ks":{"a":{"a":0,"k":[0,0]},"p":{"a":0,"k":[0,0]},"s":{"a":0,"k":[100,100]},"sk":{"a":0,"k":0},"sa":{"a":0,"k":0},"r":{"a":0,"k":0},"o":{"a":1,"k":[{"t":48,"s":[0],"o":{"x":[0.5],"y":[0.35]},"i":{"x":[0.15],"y":[1]}},{"t":138,"s":[100]}]}},"st":0,"ip":0,"op":480,"bm":0,"sr":1,"ty":4,"shapes":[{"ty":"gr","nm":"Group","hd":false,"np":3,"it":[{"ty":"sh","nm":"Path","hd":false,"ks":{"a":0,"k":{"c":false,"v":[[0.5,-0.5],[111.3258,-0.5]],"i":[[0,0],[0,0]],"o":[[0,0],[0,0]]}}},{"ty":"st","o":{"a":1,"k":[{"t":48,"s":[100],"o":{"x":[0.5],"y":[0.35]},"i":{"x":[0.15],"y":[1]}},{"t":232.52941176470492,"s":[0]}]},"c":{"a":1,"k":[{"t":48,"s":[1,0.9607843137254902,0,1],"o":{"x":[0.5],"y":[0.35]},"i":{"x":[0.15],"y":[1]}},{"t":232.52941176470492,"s":[1,0.9607843137254902,0,1]}]},"w":{"a":0,"k":1},"ml":4,"lc":1,"lj":1,"nm":"Stroke","hd":false,"d":[{"n":"o","nm":"Offset","v":{"a":0,"k":0}},{"n":"d","nm":"Dash","v":{"a":0,"k":0}},{"n":"g","nm":"Gap","v":{"a":0,"k":0}}]},{"ty":"tr","a":{"a":0,"k":[0,0]},"p":{"a":0,"k":[0,0]},"s":{"a":0,"k":[100,100]},"sk":{"a":0,"k":0},"sa":{"a":0,"k":0},"r":{"a":0,"k":0},"o":{"a":0,"k":100}}]},{"ty":"gr","nm":"Group","hd":false,"np":3,"it":[{"ty":"rc","nm":"Rectangle","hd":false,"p":{"a":0,"k":[56.4129,0.5]},"s":{"a":0,"k":[225.6516,2]},"r":{"a":0,"k":0}},{"ty":"fl","o":{"a":0,"k":0},"c":{"a":0,"k":[0,1,0,1]},"nm":"Fill","hd":false,"r":1},{"ty":"tr","a":{"a":0,"k":[0,0]},"p":{"a":0,"k":[0,0]},"s":{"a":0,"k":[100,100]},"sk":{"a":0,"k":0},"sa":{"a":0,"k":0},"r":{"a":0,"k":0},"o":{"a":0,"k":100}}]}]},{"ty":3,"ddd":0,"ind":16,"hd":false,"nm":"Rectangle 3 - Null","parent":5,"ks":{"a":{"a":0,"k":[0,17]},"o":{"a":0,"k":100},"p":{"a":0,"k":[188,133]},"r":{"a":0,"k":0},"s":{"a":0,"k":[100,100]},"sk":{"a":0,"k":0},"sa":{"a":0,"k":0}},"st":0,"ip":0,"op":480,"bm":0,"sr":1},{"ty":4,"ddd":0,"ind":17,"hd":false,"nm":"Rectangle 3","parent":16,"ks":{"a":{"a":0,"k":[0,0]},"p":{"a":0,"k":[0,0]},"s":{"a":0,"k":[100,100]},"sk":{"a":0,"k":0},"sa":{"a":0,"k":0},"r":{"a":0,"k":0},"o":{"a":0,"k":100}},"st":0,"ip":0,"op":480,"bm":0,"sr":1,"shapes":[{"ty":"gr","nm":"Group","hd":false,"np":3,"it":[{"ty":"sh","nm":"Path","hd":false,"ks":{"a":1,"k":[{"t":174.09243697478894,"s":[{"c":true,"v":[[0.01,0],[20.99,0],[21,0.01],[21,33.99],[20.99,34],[0.01,34],[0,33.99],[0,0.01],[0.01,0],[0.01,0]],"i":[[0,0],[0,0],[0,-0.0055],[0,0],[0.0055,0],[0,0],[0,0.0055],[0,0],[-0.0055,0],[0,0]],"o":[[0,0],[0.0055200000000006355,0],[0,0],[0,0.005519999999997083],[0,0],[-0.00552,0],[0,0],[0,-0.00552],[0,0],[0,0]]}],"o":{"x":[0.5],"y":[0.35]},"i":{"x":[0.15],"y":[1]}},{"t":442.4957983193271,"s":[{"c":true,"v":[[0.01,0],[99.99,0],[100,0.01],[100,33.99],[99.99,34],[0.01,34],[0,33.99],[0,0.01],[0.01,0],[0.01,0]],"i":[[0,0],[0,0],[0,-0.0055],[0,0],[0.0055,0],[0,0],[0,0.0055],[0,0],[-0.0055,0],[0,0]],"o":[[0,0],[0.005520000000004188,0],[0,0],[0,0.005519999999997083],[0,0],[-0.00552,0],[0,0],[0,-0.00552],[0,0],[0,0]]}]}]}},{"ty":"fl","o":{"a":1,"k":[{"t":165.5882352941168,"s":[100],"o":{"x":[0.5],"y":[0.35]},"i":{"x":[0.15],"y":[1]}},{"t":170.966386554621,"s":[100]}]},"c":{"a":1,"k":[{"t":165.5882352941168,"s":[0.37254901960784315,0,0,1],"o":{"x":[0.5],"y":[0.35]},"i":{"x":[0.15],"y":[1]}},{"t":170.966386554621,"s":[0.10196078431372549,0.4549019607843137,0.1568627450980392,1]}]},"nm":"Fill","hd":false,"r":1},{"ty":"tr","a":{"a":0,"k":[0,0]},"p":{"a":0,"k":[0,0]},"s":{"a":0,"k":[100,100]},"sk":{"a":0,"k":0},"sa":{"a":0,"k":0},"r":{"a":0,"k":0},"o":{"a":0,"k":100}}]}]},{"ty":3,"ddd":0,"ind":18,"hd":false,"nm":"Rectangle 2 - Null","parent":5,"ks":{"a":{"a":0,"k":[0,0]},"o":{"a":0,"k":100},"p":{"a":0,"k":[297,120]},"r":{"a":0,"k":0},"s":{"a":0,"k":[100,100]},"sk":{"a":0,"k":0},"sa":{"a":0,"k":0}},"st":0,"ip":0,"op":480,"bm":0,"sr":1},{"ty":4,"ddd":0,"ind":19,"hd":false,"nm":"Rectangle 2","parent":18,"ks":{"a":{"a":0,"k":[0,0]},"p":{"a":0,"k":[0,0]},"s":{"a":0,"k":[100,100]},"sk":{"a":0,"k":0},"sa":{"a":0,"k":0},"r":{"a":0,"k":0},"o":{"a":0,"k":100}},"st":0,"ip":0,"op":480,"bm":0,"sr":1,"shapes":[{"ty":"gr","nm":"Group","hd":false,"np":3,"it":[{"ty":"sh","nm":"Path","hd":false,"ks":{"a":0,"k":{"c":true,"v":[[0.01,0],[5.99,0],[6,0.01],[6,25.99],[5.99,26],[0.01,26],[0,25.99],[0,0.01],[0.01,0],[0.01,0]],"i":[[0,0],[0,0],[0,-0.0055],[0,0],[0.0055,0],[0,0],[0,0.0055],[0,0],[-0.0055,0],[0,0]],"o":[[0,0],[0.005519999999999747,0],[0,0],[0,0.0055200000000006355],[0,0],[-0.00552,0],[0,0],[0,-0.00552],[0,0],[0,0]]}}},{"ty":"fl","o":{"a":0,"k":100},"c":{"a":0,"k":[0,0,0,1]},"nm":"Fill","hd":false,"r":1},{"ty":"tr","a":{"a":0,"k":[0,0]},"p":{"a":0,"k":[0,0]},"s":{"a":0,"k":[100,100]},"sk":{"a":0,"k":0},"sa":{"a":0,"k":0},"r":{"a":0,"k":0},"o":{"a":0,"k":100}}]}]},{"ty":3,"ddd":0,"ind":20,"hd":false,"nm":"Rectangle 1 - Null","parent":5,"ks":{"a":{"a":0,"k":[0,0]},"o":{"a":0,"k":100},"p":{"a":0,"k":[179,105]},"r":{"a":0,"k":0},"s":{"a":0,"k":[100,100]},"sk":{"a":0,"k":0},"sa":{"a":0,"k":0}},"st":0,"ip":0,"op":480,"bm":0,"sr":1},{"ddd":0,"ind":21,"hd":false,"nm":"Rectangle 1 - Stroke","parent":20,"ks":{"a":{"a":0,"k":[0,0]},"p":{"a":0,"k":[0,0]},"s":{"a":0,"k":[100,100]},"sk":{"a":0,"k":0},"sa":{"a":0,"k":0},"r":{"a":0,"k":0},"o":{"a":0,"k":100}},"st":0,"ip":0,"op":480,"bm":0,"sr":1,"ty":4,"shapes":[{"ty":"gr","nm":"Group","hd":false,"np":3,"it":[{"ty":"sh","nm":"Path","hd":false,"ks":{"a":0,"k":{"c":true,"v":[[0.01,0],[117.99,0],[118,0.01],[118,54.99],[117.99,55],[0.01,55],[0,54.99],[0,0.01],[0.01,0],[0.01,0]],"i":[[0,0],[0,0],[0,-0.0055],[0,0],[0.0055,0],[0,0],[0,0.0055],[0,0],[-0.0055,0],[0,0]],"o":[[0,0],[0.005520000000004188,0],[0,0],[0,0.005519999999997083],[0,0],[-0.00552,0],[0,0],[0,-0.00552],[0,0],[0,0]]}}},{"ty":"st","o":{"a":0,"k":100},"c":{"a":0,"k":[0,0,0,1]},"w":{"a":0,"k":12},"ml":4,"lc":1,"lj":1,"nm":"Stroke","hd":false,"d":[{"n":"o","nm":"Offset","v":{"a":0,"k":0}},{"n":"d","nm":"Dash","v":{"a":0,"k":0}},{"n":"g","nm":"Gap","v":{"a":0,"k":0}}]},{"ty":"tr","a":{"a":0,"k":[0,0]},"p":{"a":0,"k":[0,0]},"s":{"a":0,"k":[100,100]},"sk":{"a":0,"k":0},"sa":{"a":0,"k":0},"r":{"a":0,"k":0},"o":{"a":0,"k":100}}]},{"ty":"gr","nm":"Group","hd":false,"np":3,"it":[{"ty":"rc","nm":"Rectangle","hd":false,"p":{"a":0,"k":[62,30.5]},"s":{"a":0,"k":[248,122]},"r":{"a":0,"k":0}},{"ty":"fl","o":{"a":0,"k":0},"c":{"a":0,"k":[0,1,0,1]},"nm":"Fill","hd":false,"r":1},{"ty":"tr","a":{"a":0,"k":[0,0]},"p":{"a":0,"k":[0,0]},"s":{"a":0,"k":[100,100]},"sk":{"a":0,"k":0},"sa":{"a":0,"k":0},"r":{"a":0,"k":0},"o":{"a":0,"k":100}}]}],"hasMask":true,"masksProperties":[{"nm":"Mask","pt":{"a":0,"k":{"c":true,"v":[[0.01,0],[117.99,0],[118,0.01],[118,54.99],[117.99,55],[0.01,55],[0,54.99],[0,0.01],[0.01,0],[0.01,0]],"i":[[0,0],[0,0],[0,-0.0055],[0,0],[0.0055,0],[0,0],[0,0.0055],[0,0],[-0.0055,0],[0,0]],"o":[[0,0],[0.005520000000004188,0],[0,0],[0,0.005519999999997083],[0,0],[-0.00552,0],[0,0],[0,-0.00552],[0,0],[0,0]]}},"o":{"a":0,"k":100},"mode":"a","x":{"a":0,"k":0}}]},{"ty":4,"ddd":0,"ind":22,"hd":false,"nm":"battery_icon_vector","parent":5,"ks":{"a":{"a":0,"k":[0,0]},"p":{"a":0,"k":[0,0]},"s":{"a":0,"k":[100,100]},"sk":{"a":0,"k":0},"sa":{"a":0,"k":0},"r":{"a":0,"k":0},"o":{"a":0,"k":100}},"st":0,"ip":0,"op":480,"bm":0,"sr":1,"shapes":[{"ty":"gr","nm":"Group","hd":false,"np":3,"it":[{"ty":"sh","nm":"Path","hd":false,"ks":{"a":0,"k":{"c":true,"v":[[0.01,0],[477.99,0],[478,0.01],[478,270.99],[477.99,271],[0.01,271],[0,270.99],[0,0.01],[0.01,0],[0.01,0]],"i":[[0,0],[0,0],[0,-0.0055],[0,0],[0.0055,0],[0,0],[0,0.0055],[0,0],[-0.0055,0],[0,0]],"o":[[0,0],[0.005519999999989977,0],[0,0],[0,0.005519999999989977],[0,0],[-0.00552,0],[0,0],[0,-0.00552],[0,0],[0,0]]}}},{"ty":"fl","o":{"a":0,"k":100},"c":{"a":0,"k":[0,0.03529411764705882,0.34901960784313724,1]},"nm":"Fill","hd":false,"r":1},{"ty":"tr","a":{"a":0,"k":[0,0]},"p":{"a":0,"k":[0,0]},"s":{"a":0,"k":[100,100]},"sk":{"a":0,"k":0},"sa":{"a":0,"k":0},"r":{"a":0,"k":0},"o":{"a":0,"k":100}}]}]}]}],"layers":[{"ty":3,"ddd":0,"ind":5,"hd":false,"nm":"battery_icon_vector - Null","ks":{"a":{"a":0,"k":[0,0]},"o":{"a":0,"k":100},"p":{"a":0,"k":[0,0]},"r":{"a":0,"k":0},"s":{"a":0,"k":[100,100]},"sk":{"a":0,"k":0},"sa":{"a":0,"k":0}},"st":0,"ip":0,"op":480,"bm":0,"sr":1},{"ddd":0,"ind":2,"ty":0,"nm":"battery_icon_vector","refId":"lwg7cea241s47sef","sr":1,"ks":{"a":{"a":0,"k":[0,0]},"p":{"a":0,"k":[0,0]},"s":{"a":0,"k":[100,100]},"sk":{"a":0,"k":0},"sa":{"a":0,"k":0},"r":{"a":0,"k":0},"o":{"a":0,"k":100}},"ao":0,"w":478,"h":271,"ip":0,"op":480,"st":0,"hd":false,"bm":0}],"meta":{"a":"","d":"","tc":"","g":"Aninix"}}